fisher_exact-0.0.1.dist-info/METADATA
fisher_exact-0.0.1.dist-info/WHEEL
fisher_exact/backend.py
fisher_exact/fisher_exact.cp38-win_amd64.pyd
fisher_exact/__init__.py
fisher_exact/__pycache__/backend.cpython-38.pyc
fisher_exact/__pycache__/__init__.cpython-38.pyc
fisher_exact/fisher_exact.cp39-win_amd64.pyd
fisher_exact-0.0.1.dist-info/RECORD
