Metadata-Version: 2.1
Name: fisher-exact
Version: 0.0.1
Requires-Dist: numpy>=1.11.0
Author: vlada.kunc@gmail.com
Author-Email: vlada.kunc@gmail.com
